{
  "db_name": "SQLite",
  "query": "INSERT INTO merges (\n                id, task_attempt_id, merge_type, merge_commit, created_at, target_branch_name\n            ) VALUES ($1, $2, 'direct', $3, $4, $5)\n            RETURNING \n                id as \"id!: Uuid\",\n                task_attempt_id as \"task_attempt_id!: Uuid\",\n                merge_type as \"merge_type!: MergeType\",\n                merge_commit,\n                pr_number,\n                pr_url,\n                pr_status as \"pr_status?: MergeStatus\",\n                pr_merged_at as \"pr_merged_at?: DateTime<Utc>\",\n                pr_merge_commit_sha,\n                created_at as \"created_at!: DateTime<Utc>\",\n                target_branch_name as \"target_branch_name!: String\"\n            ",
  "describe": {
    "columns": [
      {
        "name": "id!: Uuid",
        "ordinal": 0,
        "type_info": "Blob"
      },
      {
        "name": "task_attempt_id!: Uuid",
        "ordinal": 1,
        "type_info": "Blob"
      },
      {
        "name": "merge_type!: MergeType",
        "ordinal": 2,
        "type_info": "Text"
      },
      {
        "name": "merge_commit",
        "ordinal": 3,
        "type_info": "Text"
      },
      {
        "name": "pr_number",
        "ordinal": 4,
        "type_info": "Integer"
      },
      {
        "name": "pr_url",
        "ordinal": 5,
        "type_info": "Text"
      },
      {
        "name": "pr_status?: MergeStatus",
        "ordinal": 6,
        "type_info": "Text"
      },
      {
        "name": "pr_merged_at?: DateTime<Utc>",
        "ordinal": 7,
        "type_info": "Text"
      },
      {
        "name": "pr_merge_commit_sha",
        "ordinal": 8,
        "type_info": "Text"
      },
      {
        "name": "created_at!: DateTime<Utc>",
        "ordinal": 9,
        "type_info": "Text"
      },
      {
        "name": "target_branch_name!: String",
        "ordinal": 10,
        "type_info": "Text"
      }
    ],
    "parameters": {
      "Right": 5
    },
    "nullable": [
      true,
      false,
      false,
      true,
      true,
      true,
      true,
      true,
      true,
      false,
      false
    ]
  },
  "hash": "32c9dae46df6480ce1ca07f72b8659e60d9159afcc03a4bb5213f7a2bae537d8"
}
